LICENSE
README.md
setup.py
NemSec/__init__.py
NemSec/api.py
NemSec/init.py
nemsec.egg-info/PKG-INFO
nemsec.egg-info/SOURCES.txt
nemsec.egg-info/dependency_links.txt
nemsec.egg-info/requires.txt
nemsec.egg-info/top_level.txt