Metadata-Version: 2.1
Name: nemsec
Version: 1.0.0
Summary: NemSec - библиотека для обработки данных от устройств LoRaWAN
Home-page: https://github.com/artnet82/NemSec
Author: Nemtyrev Aleksey
Author-email: art.net82@gmail.com
Classifier: Development Status :: 3 - Alpha
Classifier: Intended Audience :: Developers
Classifier: License :: OSI Approved :: Apache Software License
Classifier: Programming Language :: Python :: 3
Classifier: Programming Language :: Python :: 3.7
Classifier: Programming Language :: Python :: 3.8
Classifier: Programming Language :: Python :: 3.9
License-File: LICENSE
Requires-Dist: pyota
Requires-Dist: numpy
Requires-Dist: pandas
